[{"date":"2007-01-03","time_start":"08:12:00","office":"Tribunal Constitucional","title":"Â ","meeting_place":"","id_document":"DNI","id_number":"40101837","entity":"","reason":"","host_name":"","full_name":"Angela Churichaqui Crispín","time_end":"13:01","institution":"","location":""},{"date":"2007-01-03","time_start":"08:15:00","office":"Tribunal Constitucional","title":"Â ","meeting_place":"","id_document":"DNI","id_number":"41316898","entity":"","reason":"","host_name":"","full_name":"Carmen Lázo Baca","time_end":"17:06","institution":"","location":""},{"date":"2007-01-03","time_start":"08:17:00","office":"Tribunal Constitucional","title":"Â ","meeting_place":"","id_document":"DNI","id_number":"09929497","entity":"","reason":"","host_name":"","full_name":"Miriam Handa Vargas","time_end":"17:01","institution":"","location":""},{"date":"2007-01-03","time_start":"08:17:00","office":"Tribunal Constitucional","title":"Â ","meeting_place":"","id_document":"DNI","id_number":"41064542","entity":"","reason":"","host_name":"","full_name":"Evelin Pique Buitrón","time_end":"16:38","institution":"","location":""},{"date":"2007-01-03","time_start":"08:22:00","office":"Tribunal Constitucional","title":"Â ","meeting_place":"","id_document":"DNI","id_number":"41152610","entity":"","reason":"","host_name":"","full_name":"Jilver Rodríguez Neyra","time_end":"16:57","institution":"","location":""},{"date":"2007-01-03","time_start":"08:32:00","office":"Tribunal Constitucional","title":"Â ","meeting_place":"","id_document":"DNI","id_number":"06256274","entity":"","reason":"","host_name":"","full_name":"Roger Cáceres Velásquez","time_end":"08:45","institution":"","location":""},{"date":"2007-01-03","time_start":"08:36:00","office":"Tribunal Constitucional","title":"Â ","meeting_place":"","id_document":"DNI","id_number":"09901652","entity":"","reason":"","host_name":"","full_name":"Angello Jaramillo Domínguez","time_end":"09:40","institution":"","location":""},{"date":"2007-01-03","time_start":"08:36:00","office":"Tribunal Constitucional","title":"Â ","meeting_place":"","id_document":"DNI","id_number":"25699147","entity":"","reason":"","host_name":"","full_name":"Jorge Zapata Chávez","time_end":"09:40","institution":"","location":""},{"date":"2007-01-03","time_start":"08:37:00","office":"Tribunal Constitucional","title":"Â ","meeting_place":"","id_document":"DNI","id_number":"07625246","entity":"","reason":"","host_name":"","full_name":"José Cairo Roldán","time_end":"09:30","institution":"","location":""},{"date":"2007-01-03","time_start":"08:37:00","office":"Tribunal Constitucional","title":"Â ","meeting_place":"","id_document":"DNI","id_number":"25653337","entity":"","reason":"","host_name":"","full_name":"Sara Taipe Chávez","time_end":"09:30","institution":"","location":""},{"date":"2007-01-03","time_start":"08:58:00","office":"Tribunal Constitucional","title":"Â ","meeting_place":"","id_document":"DNI","id_number":"40486975","entity":"","reason":"","host_name":"","full_name":"Alan Martínez Morón","time_end":"14:10","institution":"","location":""},{"date":"2007-01-03","time_start":"08:59:00","office":"Tribunal Constitucional","title":"Â ","meeting_place":"","id_document":"DNI","id_number":"42135109","entity":"","reason":"","host_name":"","full_name":"Liliana Salomé Resurrección","time_end":"15:15","institution":"","location":""},{"date":"2007-01-03","time_start":"09:10:00","office":"Tribunal Constitucional","title":"Â ","meeting_place":"","id_document":"DNI","id_number":"09646170","entity":"","reason":"","host_name":"","full_name":"María Quipusco Luna","time_end":"09:25","institution":"","location":""},{"date":"2007-01-03","time_start":"09:11:00","office":"Tribunal Constitucional","title":"Â ","meeting_place":"","id_document":"DNI","id_number":"10540200","entity":"","reason":"","host_name":"","full_name":"Oscar Lózano Hidalgo","time_end":"09:33","institution":"","location":""},{"date":"2007-01-03","time_start":"09:11:00","office":"Tribunal Constitucional","title":"Â ","meeting_place":"","id_document":"DNI","id_number":"08598118","entity":"","reason":"","host_name":"","full_name":"Carlos Tantaleán Rojas","time_end":"09:33","institution":"","location":""},{"date":"2007-01-03","time_start":"09:28:00","office":"Tribunal Constitucional","title":"Â ","meeting_place":"","id_document":"DNI","id_number":"25667186","entity":"","reason":"","host_name":"","full_name":"Juan Díaz Campos","time_end":"10:00","institution":"","location":""},{"date":"2007-01-03","time_start":"09:28:00","office":"Tribunal Constitucional","title":"Â ","meeting_place":"","id_document":"DNI","id_number":"25728962","entity":"","reason":"","host_name":"","full_name":"Ana Arrarte Arisnabarreta","time_end":"10:00","institution":"","location":""},{"date":"2007-01-03","time_start":"10:16:00","office":"Tribunal Constitucional","title":"Â ","meeting_place":"","id_document":"DNI","id_number":"40056837","entity":"","reason":"","host_name":"","full_name":"Giovanna Ibáñez Ambrosio","time_end":"17:00","institution":"","location":""},{"date":"2007-01-03","time_start":"11:09:00","office":"Tribunal Constitucional","title":"Â ","meeting_place":"","id_document":"DNI","id_number":"40436153","entity":"","reason":"","host_name":"","full_name":"Gerardo Lam Michue","time_end":"11:46","institution":"","location":""},{"date":"2007-01-03","time_start":"11:15:00","office":"Tribunal Constitucional","title":"Â ","meeting_place":"","id_document":"DNI","id_number":"08344264","entity":"","reason":"","host_name":"","full_name":"Humberto León Díaz","time_end":"11:17","institution":"","location":""},{"date":"2007-01-03","time_start":"11:28:00","office":"Tribunal Constitucional","title":"Â ","meeting_place":"","id_document":"DNI","id_number":"09802126","entity":"","reason":"","host_name":"","full_name":"Juan Alarcón Sandoval","time_end":"11:30","institution":"","location":""},{"date":"2007-01-03","time_start":"11:43:00","office":"Tribunal Constitucional","title":"Â ","meeting_place":"","id_document":"DNI","id_number":"40787371","entity":"","reason":"","host_name":"","full_name":"Andréa Santa Crúz Alvárez","time_end":"15:21","institution":"","location":""},{"date":"2007-01-03","time_start":"11:47:00","office":"Tribunal Constitucional","title":"Â ","meeting_place":"","id_document":"DNI","id_number":"06882014","entity":"","reason":"","host_name":"","full_name":"Richard Ruíz Camacho","time_end":"18:10","institution":"","location":""},{"date":"2007-01-03","time_start":"12:00:00","office":"Tribunal Constitucional","title":"Â ","meeting_place":"","id_document":"DNI","id_number":"10318180","entity":"","reason":"","host_name":"","full_name":"Victor Chávez Murga","time_end":"12:02","institution":"","location":""},{"date":"2007-01-03","time_start":"13:09:00","office":"Tribunal Constitucional","title":"Â ","meeting_place":"","id_document":"DNI","id_number":"07944750","entity":"","reason":"","host_name":"","full_name":"Fernando López Pichen","time_end":"13:15","institution":"","location":""},{"date":"2007-01-03","time_start":"14:38:00","office":"Tribunal Constitucional","title":"Â ","meeting_place":"","id_document":"DNI","id_number":"40770888","entity":"","reason":"","host_name":"","full_name":"Rocío Quispe Mendoza","time_end":"15:05","institution":"","location":""},{"date":"2007-01-03","time_start":"14:40:00","office":"Tribunal Constitucional","title":"Â ","meeting_place":"","id_document":"DNI","id_number":"00490598","entity":"","reason":"","host_name":"","full_name":"Santos Silva Múñoz","time_end":"15:00","institution":"","location":""},{"date":"2007-01-03","time_start":"15:10:00","office":"Tribunal Constitucional","title":"Â ","meeting_place":"","id_document":"DNI","id_number":"25830528","entity":"","reason":"","host_name":"","full_name":"Ezéquiel  Padilla Ponce","time_end":"15:40","institution":"","location":""},{"date":"2007-01-03","time_start":"15:41:00","office":"Tribunal Constitucional","title":"Â ","meeting_place":"","id_document":"DNI","id_number":"10157798","entity":"","reason":"","host_name":"","full_name":"Fredy Malpartida Huamán","time_end":"16:00","institution":"","location":""},{"date":"2007-01-03","time_start":"16:23:00","office":"Tribunal Constitucional","title":"Â ","meeting_place":"","id_document":"DNI","id_number":"06074377","entity":"","reason":"","host_name":"","full_name":"Antonio Luya Cierto","time_end":"17:17","institution":"","location":""},{"date":"2007-01-03","time_start":"Â ","office":"Tribunal Constitucional","title":"Â ","meeting_place":"","id_document":"Â ","id_number":"Â ","entity":"","reason":"","host_name":"","full_name":"Â ","time_end":"Â ","institution":"","location":""}]