[{"date":"2007-06-15","time_start":"08:24:00","office":"Tribunal Constitucional","title":"Â ","meeting_place":"","id_document":"DNI","id_number":"43547088","entity":"","reason":"Visita","host_name":"Cmdte. Bismarc Cumpa","full_name":"Napoleón Aquino Menéndez","time_end":"08:47","institution":"","location":""},{"date":"2007-06-15","time_start":"09:03:00","office":"Tribunal Constitucional","title":"Â ","meeting_place":"","id_document":"DNI","id_number":"16650828","entity":"","reason":"Visita","host_name":"Dr. Magdiel Gonzáles O.","full_name":"Carlos Quiñónez Farro","time_end":"09:14","institution":"","location":""},{"date":"2007-06-15","time_start":"16:14:00","office":"Tribunal Constitucional","title":"Â ","meeting_place":"","id_document":"DNI","id_number":"41897306","entity":"","reason":"Visita","host_name":"Dr. Carolina Canales C.","full_name":"Giorgio Massari Figali","time_end":"10:20","institution":"","location":""},{"date":"2007-06-15","time_start":"10:15:00","office":"Tribunal Constitucional","title":"Â ","meeting_place":"","id_document":"DNI","id_number":"40299320","entity":"","reason":"Visita","host_name":"Sra. Elizabeth Guevara M","full_name":"Gisell Rubin Morales","time_end":"10:30","institution":"","location":""},{"date":"2007-06-15","time_start":"10:27:00","office":"Tribunal Constitucional","title":"Â ","meeting_place":"","id_document":"DNI","id_number":"23822067","entity":"","reason":"Visita","host_name":"Dr. Juan Vergara G.","full_name":"Mateo Castañeda Segovia","time_end":"11:12","institution":"","location":""},{"date":"2007-06-15","time_start":"11:02:00","office":"Tribunal Constitucional","title":"Â ","meeting_place":"","id_document":"C.E","id_number":"00240781","entity":"","reason":"Visita","host_name":"Econ. Lucy Linares O.","full_name":"Rosa Ludin Zipman","time_end":"11:55","institution":"","location":""},{"date":"2007-06-15","time_start":"11:02:00","office":"Tribunal Constitucional","title":"Â ","meeting_place":"","id_document":"DNI","id_number":"08218448","entity":"","reason":"Visita","host_name":"Econ. Lucy Linares O.","full_name":"Roberto Manajovslki Ludin","time_end":"11:55","institution":"","location":""},{"date":"2007-06-15","time_start":"12:06:00","office":"Tribunal Constitucional","title":"Â ","meeting_place":"","id_document":"DNI","id_number":"15949548","entity":"","reason":"Visita","host_name":"Dr. Juan Bardelli L.","full_name":"Alejandro Morales Zampa","time_end":"12:23","institution":"","location":""},{"date":"2007-06-15","time_start":"12:39:00","office":"Tribunal Constitucional","title":"Â ","meeting_place":"","id_document":"DNI","id_number":"08177544","entity":"","reason":"Visita","host_name":"Srta. Patricia Rojas M.","full_name":"Moisés Gutiérrez Gutiérrez","time_end":"12:43","institution":"","location":""},{"date":"2007-06-15","time_start":"12:40:00","office":"Tribunal Constitucional","title":"Â ","meeting_place":"","id_document":"DNI","id_number":"08108404","entity":"","reason":"Proveedor","host_name":"Sr. Jorge Borda V.","full_name":"Juan Maguiña Dueñas","time_end":"13:02","institution":"","location":""},{"date":"2007-06-15","time_start":"12:43:00","office":"Tribunal Constitucional","title":"Â ","meeting_place":"","id_document":"DNI","id_number":"40299330","entity":"","reason":"Visita","host_name":"Srta. Paola Ordóñez R.","full_name":"Gisell Rubin Morales","time_end":"12:46","institution":"","location":""},{"date":"2007-06-15","time_start":"12:53:00","office":"Tribunal Constitucional","title":"Â ","meeting_place":"","id_document":"DNI","id_number":"07920348","entity":"","reason":"Visita","host_name":"CPC. Magaly Rodríguez R.","full_name":"Javier Rodríguez Rodríguez","time_end":"14:18","institution":"","location":""},{"date":"2007-06-15","time_start":"14:16:00","office":"Tribunal Constitucional","title":"Â ","meeting_place":"","id_document":"DNI","id_number":"40115129","entity":"","reason":"Visita","host_name":"Sra. Flor Ordóñez C.","full_name":"Hernando De la Vega Brisón","time_end":"15:29","institution":"","location":""},{"date":"2007-06-15","time_start":"14:16:00","office":"Tribunal Constitucional","title":"Â ","meeting_place":"","id_document":"DNI","id_number":"40934813","entity":"","reason":"Visita","host_name":"Sra. Flor Ordóñez C.","full_name":"Gloria Pari Mamani","time_end":"15:29","institution":"","location":""},{"date":"2007-06-15","time_start":"15:29:00","office":"Tribunal Constitucional","title":"Â ","meeting_place":"","id_document":"DNI","id_number":"09320652","entity":"","reason":"Visita","host_name":"Sr. Carlos Rojas M.","full_name":"Jaime Flores Mejía","time_end":"15:47","institution":"","location":""},{"date":"2007-06-15","time_start":"15:36:00","office":"Tribunal Constitucional","title":"Â ","meeting_place":"","id_document":"DNI","id_number":"40148116","entity":"","reason":"Proveedor","host_name":"Sr. Jorge Borda V.","full_name":"José Meza Chunga","time_end":"15:40","institution":"","location":""},{"date":"2007-06-15","time_start":"14:48:00","office":"Tribunal Constitucional","title":"Â ","meeting_place":"","id_document":"DNI","id_number":"17523036","entity":"","reason":"Visita","host_name":"Dr. Carlos Mesía R.","full_name":"Francis Villena Rodríguez","time_end":"16:27","institution":"","location":""},{"date":"2007-06-15","time_start":"15:48:00","office":"Tribunal Constitucional","title":"Â ","meeting_place":"","id_document":"DNI","id_number":"06152866","entity":"","reason":"Visita","host_name":"Dr. Carlos Mesía R.","full_name":"Raúl Chanamé Orbe","time_end":"16:27","institution":"","location":""},{"date":"2007-06-15","time_start":"15:52:00","office":"Tribunal Constitucional","title":"Â ","meeting_place":"","id_document":"DNI","id_number":"19834779","entity":"","reason":"Visita","host_name":"Dr. Carlos Mesía R.","full_name":"Mauro Serrano García","time_end":"16:37","institution":"","location":""},{"date":"2007-06-15","time_start":"15:52:00","office":"Tribunal Constitucional","title":"Â ","meeting_place":"","id_document":"DNI","id_number":"06247888","entity":"","reason":"Visita","host_name":"Dr. Carlos Mesía R.","full_name":"Genaro Dueñas Linares","time_end":"16:37","institution":"","location":""},{"date":"2007-06-15","time_start":"15:54:00","office":"Tribunal Constitucional","title":"Â ","meeting_place":"","id_document":"DNI","id_number":"25821477","entity":"","reason":"Visita","host_name":"Dr. Carlos Mesía R.","full_name":"Segundo Alva Flores","time_end":"16:44","institution":"","location":""},{"date":"2007-06-15","time_start":"15:54:00","office":"Tribunal Constitucional","title":"Â ","meeting_place":"","id_document":"DNI","id_number":"25690826","entity":"","reason":"Visita","host_name":"Dr. Carlos Mesía R.","full_name":"Walter Morante Manrique","time_end":"16:44","institution":"","location":""},{"date":"2007-06-15","time_start":"15:54:00","office":"Tribunal Constitucional","title":"Â ","meeting_place":"","id_document":"DNI","id_number":"25465443","entity":"","reason":"Visita","host_name":"Dr. Carlos Mesía R.","full_name":"Carlos Velásquez Rodríguez","time_end":"16:44","institution":"","location":""},{"date":"2007-06-15","time_start":"16:00:00","office":"Tribunal Constitucional","title":"Â ","meeting_place":"","id_document":"DNI","id_number":"08368151","entity":"","reason":"Visita","host_name":"Dr. Carlos Mesía R.","full_name":"Vicente De la Cruz Tolentino","time_end":"16:48","institution":"","location":""},{"date":"2007-06-15","time_start":"16:27:00","office":"Tribunal Constitucional","title":"Â ","meeting_place":"","id_document":"DNI","id_number":"09080415","entity":"","reason":"Visita","host_name":"Dr. Carlos Mesía R.","full_name":"Sergio Atarama Martínez","time_end":"17:33","institution":"","location":""},{"date":"2007-06-15","time_start":"16:10:00","office":"Tribunal Constitucional","title":"Â ","meeting_place":"","id_document":"DNI","id_number":"07882831","entity":"","reason":"Visita","host_name":"Dr. César Landa A.","full_name":"Jorge Santistevan De Noriega","time_end":"17:12","institution":"","location":""},{"date":"2007-06-15","time_start":"Â ","office":"Tribunal Constitucional","title":"Â ","meeting_place":"","id_document":"Â ","id_number":"Â ","entity":"","reason":"Â ","host_name":"Â ","full_name":"Â ","time_end":"Â ","institution":"","location":""}]