[{"date":"2008-01-18","time_start":"08:38:00","office":"Tribunal Constitucional","title":"Â ","meeting_place":"","id_document":"DNI","id_number":"25665432","entity":"","reason":"Visita","host_name":"Dr. Juan Vergara G.","full_name":"Rosa Velasco Ogata","time_end":"09:49","institution":"","location":""},{"date":"2008-01-18","time_start":"08:38:00","office":"Tribunal Constitucional","title":"Â ","meeting_place":"","id_document":"DNI","id_number":"06233161","entity":"","reason":"Visita","host_name":"Dr. Juan Vergara G.","full_name":"Isaías Sánchez Ramos","time_end":"09:23","institution":"","location":""},{"date":"2008-01-18","time_start":"08:38:00","office":"Tribunal Constitucional","title":"Â ","meeting_place":"","id_document":"DNI","id_number":"10271240","entity":"","reason":"Visita","host_name":"Dr. Juan Vergara G.","full_name":"Walter Polanco Núñez","time_end":"09:23","institution":"","location":""},{"date":"2008-01-18","time_start":"09:20:00","office":"Tribunal Constitucional","title":"Â ","meeting_place":"","id_document":"DNI","id_number":"07908423","entity":"","reason":"Visita","host_name":"Srta. María Juárez G.","full_name":"Luis Del Río Reátegui","time_end":"09:24","institution":"","location":""},{"date":"2008-01-18","time_start":"09:27:00","office":"Tribunal Constitucional","title":"Â ","meeting_place":"","id_document":"DNI","id_number":"08236949","entity":"","reason":"Visita","host_name":"Dr. Carlos Mesía R.","full_name":"Ricardo Martícorena García","time_end":"10:40","institution":"","location":""},{"date":"2008-01-18","time_start":"09:28:00","office":"Tribunal Constitucional","title":"Â ","meeting_place":"","id_document":"DNI","id_number":"06123344","entity":"","reason":"Visita","host_name":"Dr. Carlos Mesía R.","full_name":"Rosa Salas Abad","time_end":"10:22","institution":"","location":""},{"date":"2008-01-18","time_start":"09:28:00","office":"Tribunal Constitucional","title":"Â ","meeting_place":"","id_document":"DNI","id_number":"06123344","entity":"","reason":"Visita","host_name":"Dr. Carlos Mesía R.","full_name":"Héctor Perca Copa","time_end":"10:22","institution":"","location":""},{"date":"2008-01-18","time_start":"09:30:00","office":"Tribunal Constitucional","title":"Â ","meeting_place":"","id_document":"DNI","id_number":"10180904","entity":"","reason":"Visita","host_name":"Dr. Carlos Mesía R.","full_name":"Nathalie Ingaruca Ruíz","time_end":"10:47","institution":"","location":""},{"date":"2008-01-18","time_start":"09:30:00","office":"Tribunal Constitucional","title":"Â ","meeting_place":"","id_document":"DNI","id_number":"06168522","entity":"","reason":"Visita","host_name":"Dr. César Landa A.","full_name":"Mércedes Bustos Díaz","time_end":"10:24","institution":"","location":""},{"date":"2008-01-18","time_start":"09:15:00","office":"Tribunal Constitucional","title":"Â ","meeting_place":"","id_document":"DNI","id_number":"17939112","entity":"","reason":"Visita","host_name":"Sr. Carlos Rojas M.","full_name":"Fransisco Rodríguez Orbégoso","time_end":"11:22","institution":"","location":""},{"date":"2008-01-18","time_start":"09:15:00","office":"Tribunal Constitucional","title":"Â ","meeting_place":"","id_document":"DNI","id_number":"40697821","entity":"","reason":"Visita","host_name":"Dra. Miriam Handa V.","full_name":"Gustavo Jorge Rojas","time_end":"11:02","institution":"","location":""},{"date":"2008-01-18","time_start":"10:12:00","office":"Tribunal Constitucional","title":"Â ","meeting_place":"","id_document":"DNI","id_number":"10321384","entity":"","reason":"Visita","host_name":"Dr. Fernando Calle H.","full_name":"Lucía Rodríguez Miranda","time_end":"10:25","institution":"","location":""},{"date":"2008-01-18","time_start":"10:19:00","office":"Tribunal Constitucional","title":"Â ","meeting_place":"","id_document":"DNI","id_number":"06051744","entity":"","reason":"Visita","host_name":"CPC. Pilar Díaz U.","full_name":"Edilberto Rodríguez Balbuena","time_end":"10:29","institution":"","location":""},{"date":"2008-01-18","time_start":"10:20:00","office":"Tribunal Constitucional","title":"Â ","meeting_place":"","id_document":"DNI","id_number":"07575643","entity":"","reason":"Visita","host_name":"Dr. Carlos Mesía R.","full_name":"Arturo Fernández Perris","time_end":"11:13","institution":"","location":""},{"date":"2008-01-18","time_start":"10:22:00","office":"Tribunal Constitucional","title":"Â ","meeting_place":"","id_document":"DNI","id_number":"04646125","entity":"","reason":"Trámite Adm.","host_name":"CPC. Miguel Novoa F.","full_name":"David Flores Ventura","time_end":"10:32","institution":"","location":""},{"date":"2008-01-18","time_start":"10:50:00","office":"Tribunal Constitucional","title":"Â ","meeting_place":"","id_document":"DNI","id_number":"09295695","entity":"","reason":"Visita","host_name":"Dr. Fernando Calle H.","full_name":"Miguel Huanay Bonilla","time_end":"11:33","institution":"","location":""},{"date":"2008-01-18","time_start":"11:08:00","office":"Tribunal Constitucional","title":"Â ","meeting_place":"","id_document":"DNI","id_number":"40690628","entity":"","reason":"Proveedor","host_name":"Econ. Lucy Linares O.","full_name":"Juan Bances Yuptón","time_end":"11:31","institution":"","location":""},{"date":"2008-01-18","time_start":"11:08:00","office":"Tribunal Constitucional","title":"Â ","meeting_place":"","id_document":"DNI","id_number":"80376799","entity":"","reason":"Servicios","host_name":"Sr. Elmer Rosales P.","full_name":"Fortunato Villanueva Fernández","time_end":"17:30","institution":"","location":""},{"date":"2008-01-18","time_start":"11:11:00","office":"Tribunal Constitucional","title":"Â ","meeting_place":"","id_document":"DNI","id_number":"07748868","entity":"","reason":"Trámite Adm.","host_name":"Sra. Nelith Gamboa Z.","full_name":"Carlos Rojas Marcos","time_end":"11:15","institution":"","location":""},{"date":"2008-01-18","time_start":"11:12:00","office":"Tribunal Constitucional","title":"Â ","meeting_place":"","id_document":"DNI","id_number":"07781907","entity":"","reason":"Visita","host_name":"Dr. Gerardo Eto C.","full_name":"Javier De Belaunde De López","time_end":"11:48","institution":"","location":""},{"date":"2008-01-18","time_start":"11:12:00","office":"Tribunal Constitucional","title":"Â ","meeting_place":"","id_document":"DNI","id_number":"40084203","entity":"","reason":"Visita","host_name":"Dr. Gerardo Eto C.","full_name":"Ursula Indacochea Prevost","time_end":"11:48","institution":"","location":""},{"date":"2008-01-18","time_start":"11:43:00","office":"Tribunal Constitucional","title":"Â ","meeting_place":"","id_document":"DNI","id_number":"09388016","entity":"","reason":"Visita","host_name":"Dra. Patricia De los Ríos R.","full_name":"Oscar Díaz Múñoz","time_end":"16:52","institution":"","location":""},{"date":"2008-01-18","time_start":"11:45:00","office":"Tribunal Constitucional","title":"Â ","meeting_place":"","id_document":"DNI","id_number":"07938332","entity":"","reason":"Visita","host_name":"Dr. Juan Vergara G.","full_name":"César Ramírez Valencia","time_end":"11:48","institution":"","location":""},{"date":"2008-01-18","time_start":"11:48:00","office":"Tribunal Constitucional","title":"Â ","meeting_place":"","id_document":"DNI","id_number":"08618072","entity":"","reason":"Visita","host_name":"Sra. Elizabeth Guevara M.","full_name":"Miguel Paredes Vásquez","time_end":"12:07","institution":"","location":""},{"date":"2008-01-18","time_start":"13:12:00","office":"Tribunal Constitucional","title":"Â ","meeting_place":"","id_document":"DNI","id_number":"09192294","entity":"","reason":"Visita","host_name":"Srta. Pamela Roose C","full_name":"Ana Casas García","time_end":"11:56","institution":"","location":""},{"date":"2008-01-18","time_start":"11:56:00","office":"Tribunal Constitucional","title":"Â ","meeting_place":"","id_document":"DNI","id_number":"08314617","entity":"","reason":"Visita","host_name":"Sr. Carlos Ramos D.","full_name":"Juan Bazán Carrión","time_end":"12:05","institution":"","location":""},{"date":"2008-01-18","time_start":"12:16:00","office":"Tribunal Constitucional","title":"Â ","meeting_place":"","id_document":"DNI","id_number":"10606211","entity":"","reason":"Visita","host_name":"Dr. Oscar Del Río G.","full_name":"Rodrígo Prado Flores","time_end":"12:36","institution":"","location":""},{"date":"2008-01-18","time_start":"12:10:00","office":"Tribunal Constitucional","title":"Â ","meeting_place":"","id_document":"DNI","id_number":"06447240","entity":"","reason":"Visita","host_name":"Dr. Oscar Del Río G.","full_name":"Ricardo Valdivia Sánchez","time_end":"12:36","institution":"","location":""},{"date":"2008-01-18","time_start":"12:55:00","office":"Tribunal Constitucional","title":"Â ","meeting_place":"","id_document":"DNI","id_number":"40529228","entity":"","reason":"Proveedor","host_name":"Sr. Jorge Borda V.","full_name":"Gina Vargas Facundo","time_end":"13:12","institution":"","location":""},{"date":"2008-01-18","time_start":"12:59:00","office":"Tribunal Constitucional","title":"Â ","meeting_place":"","id_document":"DNI","id_number":"43473876","entity":"","reason":"Visita","host_name":"Dr. Gerardo Eto C.","full_name":"Joel Rosas Alcántara","time_end":"13:30","institution":"","location":""},{"date":"2008-01-18","time_start":"14:10:00","office":"Tribunal Constitucional","title":"Â ","meeting_place":"","id_document":"DNI","id_number":"07198184","entity":"","reason":"Trámite Adm.","host_name":"CPC. Miguel Novoa F.","full_name":"Emilio Alfaro Camerón","time_end":"14:15","institution":"","location":""},{"date":"2008-01-18","time_start":"15:03:00","office":"Tribunal Constitucional","title":"Â ","meeting_place":"","id_document":"DNI","id_number":"80106972","entity":"","reason":"Servicios","host_name":"Sr. Elmer Rosales P.","full_name":"Stalin Ramírez Ríos","time_end":"17:30","institution":"","location":""},{"date":"2008-01-18","time_start":"15:08:00","office":"Tribunal Constitucional","title":"Â ","meeting_place":"","id_document":"DNI","id_number":"40229080","entity":"","reason":"Proveedor","host_name":"Sr. Jorge Borda V.","full_name":"Jéssica Quincho Mamaní","time_end":"17:14","institution":"","location":""},{"date":"2008-01-18","time_start":"Â ","office":"Tribunal Constitucional","title":"Â ","meeting_place":"","id_document":"Â ","id_number":"Â ","entity":"","reason":"Â ","host_name":"Â ","full_name":"Â ","time_end":"Â ","institution":"","location":""}]